[
  {
    "trend_arrow": "FLAT", 
    "display_time": "2016-08-27T00:12:15-07:00", 
    "noise": 1, 
    "system_time": "2016-08-27T07:01:30-07:00", 
    "direction": "Flat", 
    "sgv": 148, 
    "dateString": "2016-08-27T00:12:15-07:00", 
    "date": 1472281935000, 
    "unfiltered": 161504, 
    "filtered": 160992, 
    "device": "openaps://cgm", 
    "rssi": 447, 
    "type": "sgv", 
    "glucose": 148
  }, 
  {
    "trend_arrow": "45_UP", 
    "display_time": "2016-08-27T00:07:14-07:00", 
    "noise": 1, 
    "system_time": "2016-08-27T06:56:30-07:00", 
    "direction": "FortyFiveUp", 
    "sgv": 148, 
    "dateString": "2016-08-27T00:07:14-07:00", 
    "device": "openaps://cgm", 
    "unfiltered": 161504, 
    "rssi": 189, 
    "date": 1472281634000, 
    "filtered": 157408, 
    "type": "sgv", 
    "glucose": 148
  }, 
  {
    "trend_arrow": "FLAT", 
    "display_time": "2016-08-27T02:52:14-07:00", 
    "noise": 1, 
    "system_time": "2016-08-27T09:41:30-07:00", 
    "direction": "Flat", 
    "sgv": 141, 
    "dateString": "2016-08-27T02:52:14-07:00", 
    "date": 1472291534000, 
    "unfiltered": 153344, 
    "filtered": 158240, 
    "device": "openaps://cgm", 
    "rssi": 445, 
    "type": "sgv", 
    "glucose": 141
  }, 
  {
    "trend_arrow": "FLAT", 
    "display_time": "2016-08-27T02:47:13-07:00", 
    "noise": 1, 
    "system_time": "2016-08-27T09:36:29-07:00", 
    "direction": "Flat", 
    "sgv": 145, 
    "dateString": "2016-08-27T02:47:13-07:00", 
    "device": "openaps://cgm", 
    "unfiltered": 156352, 
    "rssi": 197, 
    "date": 1472291233000, 
    "filtered": 160608, 
    "type": "sgv", 
    "glucose": 145
  }, 
  {
    "trend_arrow": "FLAT", 
    "display_time": "2016-08-27T03:52:14-07:00", 
    "noise": 1, 
    "system_time": "2016-08-27T10:41:29-07:00", 
    "direction": "Flat", 
    "sgv": 121, 
    "dateString": "2016-08-27T03:52:14-07:00", 
    "date": 1472295134000, 
    "unfiltered": 137472, 
    "filtered": 135680, 
    "device": "openaps://cgm", 
    "rssi": 450, 
    "type": "sgv", 
    "glucose": 121
  }, 
  {
    "trend_arrow": "FLAT", 
    "display_time": "2016-08-27T03:47:13-07:00", 
    "noise": 1, 
    "system_time": "2016-08-27T10:36:29-07:00", 
    "direction": "Flat", 
    "sgv": 120, 
    "dateString": "2016-08-27T03:47:13-07:00", 
    "device": "openaps://cgm", 
    "unfiltered": 136480, 
    "rssi": 196, 
    "date": 1472294833000, 
    "filtered": 135136, 
    "type": "sgv", 
    "glucose": 120
  }, 
  {
    "trend_arrow": "FLAT", 
    "display_time": "2016-08-27T04:02:14-07:00", 
    "noise": 1, 
    "system_time": "2016-08-27T10:51:29-07:00", 
    "direction": "Flat", 
    "sgv": 125, 
    "dateString": "2016-08-27T04:02:14-07:00", 
    "date": 1472295734000, 
    "unfiltered": 140192, 
    "filtered": 137856, 
    "device": "openaps://cgm", 
    "rssi": 450, 
    "type": "sgv", 
    "glucose": 125
  }, 
  {
    "trend_arrow": "FLAT", 
    "display_time": "2016-08-27T03:57:13-07:00", 
    "noise": 1, 
    "system_time": "2016-08-27T10:46:29-07:00", 
    "direction": "Flat", 
    "sgv": 122, 
    "dateString": "2016-08-27T03:57:13-07:00", 
    "device": "openaps://cgm", 
    "unfiltered": 138016, 
    "rssi": 196, 
    "date": 1472295433000, 
    "filtered": 136704, 
    "type": "sgv", 
    "glucose": 122
  }, 
  {
    "trend_arrow": "FLAT", 
    "display_time": "2016-08-27T04:52:14-07:00", 
    "noise": 1, 
    "system_time": "2016-08-27T11:41:29-07:00", 
    "direction": "Flat", 
    "sgv": 110, 
    "dateString": "2016-08-27T04:52:14-07:00", 
    "date": 1472298734000, 
    "unfiltered": 128048, 
    "filtered": 131584, 
    "device": "openaps://cgm", 
    "rssi": 446, 
    "type": "sgv", 
    "glucose": 110
  }, 
  {
    "trend_arrow": "FLAT", 
    "display_time": "2016-08-27T04:47:13-07:00", 
    "noise": 1, 
    "system_time": "2016-08-27T11:36:29-07:00", 
    "direction": "Flat", 
    "sgv": 112, 
    "dateString": "2016-08-27T04:47:13-07:00", 
    "device": "openaps://cgm", 
    "unfiltered": 129760, 
    "rssi": 194, 
    "date": 1472298433000, 
    "filtered": 133248, 
    "type": "sgv", 
    "glucose": 112
  }, 
  {
    "trend_arrow": "FLAT", 
    "display_time": "2016-08-27T07:37:13-07:00", 
    "noise": 1, 
    "system_time": "2016-08-27T14:26:28-07:00", 
    "direction": "Flat", 
    "sgv": 110, 
    "dateString": "2016-08-27T07:37:13-07:00", 
    "device": "openaps://cgm", 
    "unfiltered": 128624, 
    "rssi": 194, 
    "date": 1472308633000, 
    "filtered": 128112, 
    "type": "sgv", 
    "glucose": 110
  }, 
  {
    "trend_arrow": "FLAT", 
    "display_time": "2016-08-27T07:32:12-07:00", 
    "noise": 1, 
    "system_time": "2016-08-27T14:21:28-07:00", 
    "direction": "Flat", 
    "sgv": 109, 
    "dateString": "2016-08-27T07:32:12-07:00", 
    "date": 1472308332000, 
    "unfiltered": 127904, 
    "filtered": 126832, 
    "device": "openaps://cgm", 
    "rssi": 193, 
    "type": "sgv", 
    "glucose": 109
  }, 
  {
    "trend_arrow": "FLAT", 
    "display_time": "2016-08-27T09:17:13-07:00", 
    "noise": 1, 
    "system_time": "2016-08-27T16:06:28-07:00", 
    "direction": "Flat", 
    "sgv": 101, 
    "dateString": "2016-08-27T09:17:13-07:00", 
    "device": "openaps://cgm", 
    "unfiltered": 121360, 
    "rssi": 444, 
    "date": 1472314633000, 
    "filtered": 121328, 
    "type": "sgv", 
    "glucose": 101
  }, 
  {
    "trend_arrow": "FLAT", 
    "display_time": "2016-08-27T09:12:12-07:00", 
    "noise": 1, 
    "system_time": "2016-08-27T16:01:28-07:00", 
    "direction": "Flat", 
    "sgv": 99, 
    "dateString": "2016-08-27T09:12:12-07:00", 
    "date": 1472314332000, 
    "unfiltered": 119536, 
    "filtered": 122208, 
    "device": "openaps://cgm", 
    "rssi": 194, 
    "type": "sgv", 
    "glucose": 99
  }, 
  {
    "trend_arrow": "FLAT", 
    "display_time": "2016-08-27T10:02:13-07:00", 
    "noise": 1, 
    "system_time": "2016-08-27T16:51:28-07:00", 
    "direction": "Flat", 
    "sgv": 112, 
    "dateString": "2016-08-27T10:02:13-07:00", 
    "device": "openaps://cgm", 
    "date": 1472317333000, 
    "type": "sgv", 
    "glucose": 112
  }, 
  {
    "trend_arrow": "FLAT", 
    "display_time": "2016-08-27T10:02:13-07:00", 
    "noise": 1, 
    "system_time": "2016-08-27T16:51:28-07:00", 
    "direction": "Flat", 
    "sgv": 112, 
    "dateString": "2016-08-27T10:02:13-07:00", 
    "date": 1472317333000, 
    "unfiltered": 134816, 
    "filtered": 136160, 
    "device": "openaps://cgm", 
    "rssi": 175, 
    "type": "sgv", 
    "glucose": 112
  }, 
  {
    "trend_arrow": "FLAT", 
    "display_time": "2016-08-27T10:02:13-07:00", 
    "noise": 1, 
    "system_time": "2016-08-27T16:51:28-07:00", 
    "direction": "Flat", 
    "sgv": 113, 
    "dateString": "2016-08-27T10:02:13-07:00", 
    "device": "openaps://cgm", 
    "unfiltered": 130752, 
    "rssi": 200, 
    "date": 1472317333000, 
    "filtered": 135648, 
    "type": "sgv", 
    "glucose": 113
  }, 
  {
    "trend_arrow": "FLAT", 
    "display_time": "2016-08-27T09:57:12-07:00", 
    "noise": 1, 
    "system_time": "2016-08-27T16:46:28-07:00", 
    "direction": "Flat", 
    "sgv": 117, 
    "dateString": "2016-08-27T09:57:12-07:00", 
    "date": 1472317032000, 
    "device": "openaps://cgm", 
    "type": "sgv", 
    "glucose": 117
  }, 
  {
    "trend_arrow": "FLAT", 
    "display_time": "2016-08-27T09:57:12-07:00", 
    "noise": 1, 
    "system_time": "2016-08-27T16:46:28-07:00", 
    "direction": "Flat", 
    "sgv": 117, 
    "dateString": "2016-08-27T09:57:12-07:00", 
    "date": 1472317032000, 
    "unfiltered": 134816, 
    "filtered": 136160, 
    "device": "openaps://cgm", 
    "rssi": 175, 
    "type": "sgv", 
    "glucose": 117
  }, 
  {
    "trend_arrow": "FLAT", 
    "display_time": "2016-08-27T09:57:12-07:00", 
    "noise": 1, 
    "system_time": "2016-08-27T16:46:28-07:00", 
    "direction": "Flat", 
    "sgv": 117, 
    "dateString": "2016-08-27T09:57:12-07:00", 
    "device": "openaps://cgm", 
    "unfiltered": 136576, 
    "rssi": 168, 
    "date": 1472317032000, 
    "filtered": 135328, 
    "type": "sgv", 
    "glucose": 117
  }, 
  {
    "trend_arrow": "FLAT", 
    "display_time": "2016-08-27T12:37:12-07:00", 
    "noise": 1, 
    "system_time": "2016-08-27T19:26:27-07:00", 
    "direction": "Flat", 
    "sgv": 228, 
    "dateString": "2016-08-27T12:37:12-07:00", 
    "date": 1472326632000, 
    "unfiltered": 222880, 
    "filtered": 216832, 
    "device": "openaps://cgm", 
    "rssi": 205, 
    "type": "sgv", 
    "glucose": 228
  }, 
  {
    "trend_arrow": "FLAT", 
    "display_time": "2016-08-27T12:32:11-07:00", 
    "noise": 1, 
    "system_time": "2016-08-27T19:21:27-07:00", 
    "direction": "Flat", 
    "sgv": 222, 
    "dateString": "2016-08-27T12:32:11-07:00", 
    "device": "openaps://cgm", 
    "unfiltered": 218208, 
    "rssi": 217, 
    "date": 1472326331000, 
    "filtered": 215232, 
    "type": "sgv", 
    "glucose": 222
  }, 
  {
    "trend_arrow": "FLAT", 
    "display_time": "2016-08-27T12:57:12-07:00", 
    "noise": 1, 
    "system_time": "2016-08-27T19:46:27-07:00", 
    "direction": "Flat", 
    "sgv": 236, 
    "dateString": "2016-08-27T12:57:12-07:00", 
    "date": 1472327832000, 
    "unfiltered": 228896, 
    "filtered": 229248, 
    "device": "openaps://cgm", 
    "rssi": 441, 
    "type": "sgv", 
    "glucose": 236
  }, 
  {
    "trend_arrow": "FLAT", 
    "display_time": "2016-08-27T12:52:11-07:00", 
    "noise": 1, 
    "system_time": "2016-08-27T19:41:27-07:00", 
    "direction": "Flat", 
    "sgv": 235, 
    "dateString": "2016-08-27T12:52:11-07:00", 
    "device": "openaps://cgm", 
    "unfiltered": 228224, 
    "rssi": 180, 
    "date": 1472327531000, 
    "filtered": 227360, 
    "type": "sgv", 
    "glucose": 235
  }, 
  {
    "trend_arrow": "45_DOWN", 
    "display_time": "2016-08-27T17:57:11-07:00", 
    "noise": 1, 
    "system_time": "2016-08-28T00:46:26-07:00", 
    "direction": "FortyFiveDown", 
    "sgv": 61, 
    "dateString": "2016-08-27T17:57:11-07:00", 
    "date": 1472345831000, 
    "unfiltered": 88608, 
    "filtered": 94064, 
    "device": "openaps://cgm", 
    "rssi": 456, 
    "type": "sgv", 
    "glucose": 61
  }, 
  {
    "trend_arrow": "SINGLE_DOWN", 
    "display_time": "2016-08-27T17:52:10-07:00", 
    "noise": 1, 
    "system_time": "2016-08-28T00:41:26-07:00", 
    "direction": "SingleDown", 
    "sgv": 62, 
    "dateString": "2016-08-27T17:52:10-07:00", 
    "device": "openaps://cgm", 
    "unfiltered": 89664, 
    "rssi": 196, 
    "date": 1472345530000, 
    "filtered": 101664, 
    "type": "sgv", 
    "glucose": 62
  }, 
  {
    "trend_arrow": "FLAT", 
    "display_time": "2016-08-27T18:32:11-07:00", 
    "noise": 1, 
    "system_time": "2016-08-28T01:21:26-07:00", 
    "direction": "Flat", 
    "sgv": 109, 
    "dateString": "2016-08-27T18:32:11-07:00", 
    "device": "openaps://cgm", 
    "unfiltered": 127744, 
    "rssi": 440, 
    "date": 1472347931000, 
    "filtered": 128784, 
    "type": "sgv", 
    "glucose": 109
  }, 
  {
    "trend_arrow": "45_UP", 
    "display_time": "2016-08-27T18:27:10-07:00", 
    "noise": 1, 
    "system_time": "2016-08-28T01:16:26-07:00", 
    "direction": "FortyFiveUp", 
    "sgv": 111, 
    "dateString": "2016-08-27T18:27:10-07:00", 
    "date": 1472347630000, 
    "unfiltered": 128672, 
    "filtered": 126464, 
    "device": "openaps://cgm", 
    "rssi": 183, 
    "type": "sgv", 
    "glucose": 111
  }, 
  {
    "trend_arrow": "SINGLE_DOWN", 
    "display_time": "2016-08-27T19:22:11-07:00", 
    "noise": 1, 
    "system_time": "2016-08-28T02:11:26-07:00", 
    "direction": "SingleDown", 
    "sgv": 57, 
    "dateString": "2016-08-27T19:22:11-07:00", 
    "device": "openaps://cgm", 
    "unfiltered": 85648, 
    "rssi": 433, 
    "date": 1472350931000, 
    "filtered": 101568, 
    "type": "sgv", 
    "glucose": 57
  }, 
  {
    "trend_arrow": "45_DOWN", 
    "display_time": "2016-08-27T19:17:10-07:00", 
    "noise": 1, 
    "system_time": "2016-08-28T02:06:26-07:00", 
    "direction": "FortyFiveDown", 
    "sgv": 67, 
    "dateString": "2016-08-27T19:17:10-07:00", 
    "date": 1472350630000, 
    "unfiltered": 93840, 
    "filtered": 108656, 
    "device": "openaps://cgm", 
    "rssi": 180, 
    "type": "sgv", 
    "glucose": 67
  }, 
  {
    "trend_arrow": "45_UP", 
    "display_time": "2016-08-27T22:02:09-07:00", 
    "noise": 1, 
    "system_time": "2016-08-28T04:51:25-07:00", 
    "direction": "FortyFiveUp", 
    "sgv": 76, 
    "dateString": "2016-08-27T22:02:09-07:00", 
    "date": 1472360529000, 
    "unfiltered": 100704, 
    "filtered": 94032, 
    "device": "openaps://cgm", 
    "rssi": 185, 
    "type": "sgv", 
    "glucose": 76
  }, 
  {
    "trend_arrow": "45_UP", 
    "display_time": "2016-08-27T21:52:10-07:00", 
    "noise": 1, 
    "system_time": "2016-08-28T04:41:25-07:00", 
    "direction": "FortyFiveUp", 
    "sgv": 70, 
    "dateString": "2016-08-27T21:52:10-07:00", 
    "date": 1472359930000, 
    "unfiltered": 95840, 
    "filtered": 79536, 
    "device": "openaps://cgm", 
    "rssi": 182, 
    "type": "sgv", 
    "glucose": 70
  }, 
  {
    "trend_arrow": "45_UP", 
    "display_time": "2016-08-27T22:07:10-07:00", 
    "noise": 1, 
    "system_time": "2016-08-28T04:56:26-07:00", 
    "direction": "FortyFiveUp", 
    "sgv": 78, 
    "dateString": "2016-08-27T22:07:10-07:00", 
    "date": 1472360830000, 
    "unfiltered": 102352, 
    "filtered": 100992, 
    "device": "openaps://cgm", 
    "rssi": 694, 
    "type": "sgv", 
    "glucose": 78
  }, 
  {
    "trend_arrow": "45_UP", 
    "display_time": "2016-08-27T22:02:09-07:00", 
    "noise": 1, 
    "system_time": "2016-08-28T04:51:25-07:00", 
    "direction": "FortyFiveUp", 
    "sgv": 76, 
    "dateString": "2016-08-27T22:02:09-07:00", 
    "date": 1472360529000, 
    "unfiltered": 100704, 
    "filtered": 94032, 
    "device": "openaps://cgm", 
    "rssi": 185, 
    "type": "sgv", 
    "glucose": 76
  }
]