[
  {
    "trend_arrow": "FLAT", 
    "display_time": "2016-09-13T04:36:06-07:00", 
    "noise": 1, 
    "system_time": "2016-09-13T10:30:34-07:00", 
    "direction": "Flat", 
    "sgv": 150, 
    "dateString": "2016-09-13T04:36:06-07:00", 
    "date": 1473766566000, 
    "unfiltered": 156384, 
    "filtered": 159552, 
    "device": "openaps://indy-e1/cgm", 
    "rssi": 186, 
    "type": "sgv", 
    "glucose": 150
  }, 
  {
    "trend_arrow": "FLAT", 
    "display_time": "2016-09-13T04:31:06-07:00", 
    "noise": 1, 
    "system_time": "2016-09-13T10:25:34-07:00", 
    "direction": "Flat", 
    "sgv": 151, 
    "dateString": "2016-09-13T04:31:06-07:00", 
    "date": 1473766266000, 
    "unfiltered": 157632, 
    "filtered": 162336, 
    "device": "openaps://indy-e1/cgm", 
    "rssi": 185, 
    "type": "sgv", 
    "glucose": 151
  }
]