[
  {
    "trend_arrow": "FLAT", 
    "display_time": "2016-09-14T16:15:22-07:00", 
    "noise": 1, 
    "system_time": "2016-09-14T23:04:13-07:00", 
    "direction": "Flat", 
    "sgv": 122, 
    "dateString": "2016-09-14T16:15:22-07:00", 
    "date": 1473894922000, 
    "unfiltered": 123424, 
    "filtered": 120240, 
    "device": "openaps://indy-e1/cgm", 
    "rssi": 212, 
    "type": "sgv", 
    "glucose": 122
  }, 
  {
    "trend_arrow": "FLAT", 
    "display_time": "2016-09-14T16:10:22-07:00", 
    "noise": 1, 
    "system_time": "2016-09-14T22:59:13-07:00", 
    "direction": "Flat", 
    "sgv": 118, 
    "dateString": "2016-09-14T16:10:22-07:00", 
    "date": 1473894622000, 
    "unfiltered": 120544, 
    "filtered": 118656, 
    "device": "openaps://indy-e1/cgm", 
    "rssi": 214, 
    "type": "sgv", 
    "glucose": 118
  }
]