[
  {
    "trend_arrow": "FLAT", 
    "display_time": "2016-09-02T17:55:43-07:00", 
    "noise": 1, 
    "system_time": "2016-09-02T23:50:26-07:00", 
    "direction": "Flat", 
    "sgv": 61, 
    "dateString": "2016-09-02T17:55:43-07:00", 
    "date": 1472864143000, 
    "unfiltered": 77584, 
    "filtered": 75632, 
    "device": "openaps://cgm", 
    "rssi": 188, 
    "type": "sgv", 
    "glucose": 61
  }, 
  {
    "trend_arrow": "45_DOWN", 
    "display_time": "2016-09-02T17:50:44-07:00", 
    "noise": 1, 
    "system_time": "2016-09-02T23:45:26-07:00", 
    "direction": "FortyFiveDown", 
    "sgv": 57, 
    "dateString": "2016-09-02T17:50:44-07:00", 
    "date": 1472863844000, 
    "unfiltered": 74432, 
    "filtered": 78976, 
    "device": "openaps://cgm", 
    "rssi": 191, 
    "type": "sgv", 
    "glucose": 57
  }
]