[
  {
    "trend_arrow": "SINGLE_UP", 
    "display_time": "2016-08-29T17:45:57-07:00", 
    "noise": 1, 
    "system_time": "2016-08-29T23:40:40-07:00", 
    "direction": "SingleUp", 
    "sgv": 135, 
    "dateString": "2016-08-29T17:45:57-07:00", 
    "date": 1472517957000, 
    "unfiltered": 134592, 
    "filtered": 122720, 
    "device": "openaps://cgm", 
    "rssi": 201, 
    "type": "sgv", 
    "glucose": 135
  }, 
  {
    "trend_arrow": "45_UP", 
    "display_time": "2016-08-29T17:40:57-07:00", 
    "noise": 1, 
    "system_time": "2016-08-29T23:35:40-07:00", 
    "direction": "FortyFiveUp", 
    "sgv": 126, 
    "dateString": "2016-08-29T17:40:57-07:00", 
    "date": 1472517657000, 
    "unfiltered": 128752, 
    "filtered": 115024, 
    "device": "openaps://cgm", 
    "rssi": 194, 
    "type": "sgv", 
    "glucose": 126
  }
]