[
  {
    "trend_arrow": "FLAT", 
    "display_time": "2016-09-23T07:25:04-07:00", 
    "noise": 1, 
    "system_time": "2016-09-23T14:13:42-07:00", 
    "direction": "Flat", 
    "sgv": 93, 
    "dateString": "2016-09-23T07:25:04-07:00", 
    "date": 1474640704000, 
    "unfiltered": 102544, 
    "filtered": 105408, 
    "device": "openaps://indy-e1/cgm", 
    "rssi": 213, 
    "type": "sgv", 
    "glucose": 93
  }, 
  {
    "trend_arrow": "FLAT", 
    "display_time": "2016-09-23T07:20:04-07:00", 
    "noise": 1, 
    "system_time": "2016-09-23T14:08:42-07:00", 
    "direction": "Flat", 
    "sgv": 94, 
    "dateString": "2016-09-23T07:20:04-07:00", 
    "date": 1474640404000, 
    "unfiltered": 103536, 
    "filtered": 109216, 
    "device": "openaps://indy-e1/cgm", 
    "rssi": 204, 
    "type": "sgv", 
    "glucose": 94
  }
]