[
  {
    "trend_arrow": "FLAT", 
    "display_time": "2016-08-28T00:22:09-07:00", 
    "noise": 1, 
    "system_time": "2016-08-28T07:11:24-07:00", 
    "direction": "Flat", 
    "sgv": 140, 
    "dateString": "2016-08-28T00:22:09-07:00", 
    "date": 1472368929000, 
    "unfiltered": 152224, 
    "filtered": 145664, 
    "device": "openaps://cgm", 
    "rssi": 166, 
    "type": "sgv", 
    "glucose": 140
  }, 
  {
    "trend_arrow": "FLAT", 
    "display_time": "2016-08-28T00:17:09-07:00", 
    "noise": 1, 
    "system_time": "2016-08-28T07:06:25-07:00", 
    "direction": "Flat", 
    "sgv": 135, 
    "dateString": "2016-08-28T00:17:09-07:00", 
    "date": 1472368629000, 
    "unfiltered": 148384, 
    "filtered": 141856, 
    "device": "openaps://cgm", 
    "rssi": 185, 
    "type": "sgv", 
    "glucose": 135
  }
]