[
  {
    "trend_arrow": "FLAT", 
    "display_time": "2016-08-24T04:47:20-07:00", 
    "noise": 1, 
    "system_time": "2016-08-24T10:42:14-07:00", 
    "direction": "Flat", 
    "sgv": 105, 
    "dateString": "2016-08-24T04:47:20-07:00", 
    "date": 1472039240000, 
    "unfiltered": 122912, 
    "filtered": 117664, 
    "device": "openaps://cgm", 
    "rssi": 203, 
    "type": "sgv", 
    "glucose": 105
  }, 
  {
    "trend_arrow": "FLAT", 
    "display_time": "2016-08-24T04:42:20-07:00", 
    "noise": 1, 
    "system_time": "2016-08-24T10:37:14-07:00", 
    "direction": "Flat", 
    "sgv": 102, 
    "dateString": "2016-08-24T04:42:20-07:00", 
    "date": 1472038940000, 
    "unfiltered": 120064, 
    "filtered": 114576, 
    "device": "openaps://cgm", 
    "rssi": 185, 
    "type": "sgv", 
    "glucose": 102
  }
]