[
  {
    "trend_arrow": "FLAT", 
    "display_time": "2016-09-17T09:25:13-07:00", 
    "noise": 1, 
    "system_time": "2016-09-17T16:14:03-07:00", 
    "direction": "Flat", 
    "sgv": 126, 
    "dateString": "2016-09-17T09:25:13-07:00", 
    "date": 1474129513000, 
    "unfiltered": 128736, 
    "filtered": 127232, 
    "device": "openaps://indy-e1/cgm", 
    "rssi": 198, 
    "type": "sgv", 
    "glucose": 126
  }, 
  {
    "trend_arrow": "FLAT", 
    "display_time": "2016-09-17T09:20:13-07:00", 
    "noise": 1, 
    "system_time": "2016-09-17T16:09:03-07:00", 
    "direction": "Flat", 
    "sgv": 124, 
    "dateString": "2016-09-17T09:20:13-07:00", 
    "date": 1474129213000, 
    "unfiltered": 127392, 
    "filtered": 124896, 
    "device": "openaps://indy-e1/cgm", 
    "rssi": 195, 
    "type": "sgv", 
    "glucose": 124
  }
]