[
  {
    "trend_arrow": "FLAT", 
    "display_time": "2016-09-17T10:55:12-07:00", 
    "noise": 1, 
    "system_time": "2016-09-17T17:44:03-07:00", 
    "direction": "Flat", 
    "sgv": 104, 
    "dateString": "2016-09-17T10:55:12-07:00", 
    "date": 1474134912000, 
    "unfiltered": 108112, 
    "filtered": 114560, 
    "device": "openaps://indy-e1/cgm", 
    "rssi": 202, 
    "type": "sgv", 
    "glucose": 104
  }, 
  {
    "trend_arrow": "FLAT", 
    "display_time": "2016-09-17T10:50:12-07:00", 
    "noise": 1, 
    "system_time": "2016-09-17T17:39:03-07:00", 
    "direction": "Flat", 
    "sgv": 106, 
    "dateString": "2016-09-17T10:50:12-07:00", 
    "date": 1474134612000, 
    "unfiltered": 110160, 
    "filtered": 118944, 
    "device": "openaps://indy-e1/cgm", 
    "rssi": 195, 
    "type": "sgv", 
    "glucose": 106
  }
]