[
  {
    "trend_arrow": "FLAT", 
    "display_time": "2016-08-31T01:20:53-07:00", 
    "noise": 1, 
    "system_time": "2016-08-31T07:15:35-07:00", 
    "direction": "Flat", 
    "sgv": 152, 
    "dateString": "2016-08-31T01:20:53-07:00", 
    "date": 1472631653000, 
    "unfiltered": 189408, 
    "filtered": 191776, 
    "device": "openaps://cgm", 
    "rssi": 199, 
    "type": "sgv", 
    "glucose": 152
  }, 
  {
    "trend_arrow": "45_DOWN", 
    "display_time": "2016-08-31T01:15:53-07:00", 
    "noise": 1, 
    "system_time": "2016-08-31T07:10:35-07:00", 
    "direction": "FortyFiveDown", 
    "sgv": 150, 
    "dateString": "2016-08-31T01:15:53-07:00", 
    "date": 1472631353000, 
    "unfiltered": 188032, 
    "filtered": 195712, 
    "device": "openaps://cgm", 
    "rssi": 178, 
    "type": "sgv", 
    "glucose": 150
  }
]