[
  {
    "trend_arrow": "FLAT", 
    "display_time": "2016-08-25T00:32:16-07:00", 
    "noise": 1, 
    "system_time": "2016-08-25T06:27:09-07:00", 
    "direction": "Flat", 
    "sgv": 215, 
    "dateString": "2016-08-25T00:32:16-07:00", 
    "date": 1472110336000, 
    "unfiltered": 230912, 
    "filtered": 228128, 
    "device": "openaps://cgm", 
    "rssi": 187, 
    "type": "sgv", 
    "glucose": 215
  }, 
  {
    "trend_arrow": "FLAT", 
    "display_time": "2016-08-25T00:27:16-07:00", 
    "noise": 1, 
    "system_time": "2016-08-25T06:22:10-07:00", 
    "direction": "Flat", 
    "sgv": 213, 
    "dateString": "2016-08-25T00:27:16-07:00", 
    "date": 1472110036000, 
    "unfiltered": 229152, 
    "filtered": 227072, 
    "device": "openaps://cgm", 
    "rssi": 187, 
    "type": "sgv", 
    "glucose": 213
  }
]