[
  {
    "trend_arrow": "FLAT", 
    "display_time": "2016-08-23T21:02:22-07:00", 
    "noise": 1, 
    "system_time": "2016-08-24T02:57:15-07:00", 
    "direction": "Flat", 
    "sgv": 98, 
    "dateString": "2016-08-23T21:02:22-07:00", 
    "device": "openaps://cgm", 
    "unfiltered": 120976, 
    "rssi": 168, 
    "date": 1472011342000, 
    "filtered": 114288, 
    "type": "sgv", 
    "glucose": 98
  }, 
  {
    "trend_arrow": "FLAT", 
    "display_time": "2016-08-23T20:57:22-07:00", 
    "noise": 1, 
    "system_time": "2016-08-24T02:52:15-07:00", 
    "direction": "Flat", 
    "sgv": 91, 
    "dateString": "2016-08-23T20:57:22-07:00", 
    "device": "openaps://cgm", 
    "unfiltered": 114240, 
    "rssi": 192, 
    "date": 1472011042000, 
    "filtered": 111952, 
    "type": "sgv", 
    "glucose": 91
  }
]