[
  {
    "trend_arrow": "SINGLE_UP", 
    "system_time": "2016-08-21T00:52:30", 
    "noise": 1, 
    "direction": "SingleUp", 
    "sgv": 204, 
    "display_time": "2016-08-20T18:57:37", 
    "date": 1471744657000.0, 
    "dateString": "2016-08-20T18:57:37", 
    "unfiltered": 252960, 
    "filtered": 234336, 
    "device": "openaps://cgm", 
    "rssi": 205, 
    "type": "sgv", 
    "glucose": 204
  }, 
  {
    "trend_arrow": "45_UP", 
    "system_time": "2016-08-21T00:47:30", 
    "noise": 1, 
    "direction": "FortyFiveUp", 
    "sgv": 191, 
    "display_time": "2016-08-20T18:52:37", 
    "date": 1471744357000.0, 
    "dateString": "2016-08-20T18:52:37", 
    "unfiltered": 238912, 
    "filtered": 227424, 
    "device": "openaps://cgm", 
    "rssi": 209, 
    "type": "sgv", 
    "glucose": 191
  }, 
  {
    "trend_arrow": "45_UP", 
    "system_time": "2016-08-21T00:42:30", 
    "noise": 1, 
    "direction": "FortyFiveUp", 
    "sgv": 182, 
    "display_time": "2016-08-20T18:47:37", 
    "date": 1471744057000.0, 
    "dateString": "2016-08-20T18:47:37", 
    "unfiltered": 229024, 
    "filtered": 221888, 
    "device": "openaps://cgm", 
    "rssi": 204, 
    "type": "sgv", 
    "glucose": 182
  }, 
  {
    "trend_arrow": "45_UP", 
    "system_time": "2016-08-21T00:37:30", 
    "noise": 1, 
    "direction": "FortyFiveUp", 
    "sgv": 177, 
    "display_time": "2016-08-20T18:42:37", 
    "date": 1471743757000.0, 
    "dateString": "2016-08-20T18:42:37", 
    "unfiltered": 223456, 
    "filtered": 216064, 
    "device": "openaps://cgm", 
    "rssi": 206, 
    "type": "sgv", 
    "glucose": 177
  }, 
  {
    "trend_arrow": "45_UP", 
    "system_time": "2016-08-21T00:32:31", 
    "noise": 1, 
    "direction": "FortyFiveUp", 
    "sgv": 174, 
    "display_time": "2016-08-20T18:37:37", 
    "date": 1471743457000.0, 
    "dateString": "2016-08-20T18:37:37", 
    "unfiltered": 220224, 
    "filtered": 210336, 
    "device": "openaps://cgm", 
    "rssi": 208, 
    "type": "sgv", 
    "glucose": 174
  }, 
  {
    "trend_arrow": "FLAT", 
    "system_time": "2016-08-21T00:27:30", 
    "noise": 1, 
    "direction": "Flat", 
    "sgv": 169, 
    "display_time": "2016-08-20T18:32:37", 
    "date": 1471743157000.0, 
    "dateString": "2016-08-20T18:32:37", 
    "unfiltered": 214944, 
    "filtered": 206048, 
    "device": "openaps://cgm", 
    "rssi": 204, 
    "type": "sgv", 
    "glucose": 169
  }
]