[
  {
    "trend_arrow": "FLAT", 
    "system_time": "2016-08-25T01:12:11", 
    "noise": 1, 
    "direction": "Flat", 
    "sgv": 85, 
    "display_time": "2016-08-24T19:17:17", 
    "date": 1472091437000.0, 
    "dateString": "2016-08-24T19:17:17", 
    "unfiltered": 104608, 
    "filtered": 108304, 
    "device": "openaps://cgm", 
    "rssi": 189, 
    "type": "sgv", 
    "glucose": 85
  }, 
  {
    "trend_arrow": "FLAT", 
    "system_time": "2016-08-25T01:07:11", 
    "noise": 1, 
    "direction": "Flat", 
    "sgv": 87, 
    "display_time": "2016-08-24T19:12:17", 
    "date": 1472091137000.0, 
    "dateString": "2016-08-24T19:12:17", 
    "unfiltered": 106784, 
    "filtered": 110272, 
    "device": "openaps://cgm", 
    "rssi": 201, 
    "type": "sgv", 
    "glucose": 87
  }, 
  {
    "trend_arrow": "FLAT", 
    "system_time": "2016-08-25T01:02:11", 
    "noise": 1, 
    "direction": "Flat", 
    "sgv": 90, 
    "display_time": "2016-08-24T19:07:17", 
    "date": 1472090837000.0, 
    "dateString": "2016-08-24T19:07:17", 
    "unfiltered": 109104, 
    "filtered": 111376, 
    "device": "openaps://cgm", 
    "rssi": 192, 
    "type": "sgv", 
    "glucose": 90
  }, 
  {
    "trend_arrow": "FLAT", 
    "system_time": "2016-08-25T00:57:11", 
    "noise": 1, 
    "direction": "Flat", 
    "sgv": 91, 
    "display_time": "2016-08-24T19:02:17", 
    "date": 1472090537000.0, 
    "dateString": "2016-08-24T19:02:17", 
    "unfiltered": 110816, 
    "filtered": 111472, 
    "device": "openaps://cgm", 
    "rssi": 199, 
    "type": "sgv", 
    "glucose": 91
  }, 
  {
    "trend_arrow": "FLAT", 
    "system_time": "2016-08-25T00:52:11", 
    "noise": 1, 
    "direction": "Flat", 
    "sgv": 92, 
    "display_time": "2016-08-24T18:57:17", 
    "date": 1472090237000.0, 
    "dateString": "2016-08-24T18:57:17", 
    "unfiltered": 111664, 
    "filtered": 110832, 
    "device": "openaps://cgm", 
    "rssi": 209, 
    "type": "sgv", 
    "glucose": 92
  }, 
  {
    "trend_arrow": "FLAT", 
    "system_time": "2016-08-25T00:47:11", 
    "noise": 1, 
    "direction": "Flat", 
    "sgv": 92, 
    "display_time": "2016-08-24T18:52:17", 
    "date": 1472089937000.0, 
    "dateString": "2016-08-24T18:52:17", 
    "unfiltered": 111552, 
    "filtered": 110272, 
    "device": "openaps://cgm", 
    "rssi": 184, 
    "type": "sgv", 
    "glucose": 92
  }
]