[
  {
    "trend_arrow": "FLAT", 
    "display_time": "2016-08-25T12:17:14-07:00", 
    "noise": 1, 
    "system_time": "2016-08-25T18:12:07-07:00", 
    "direction": "Flat", 
    "sgv": 123, 
    "dateString": "2016-08-25T12:17:14-07:00", 
    "device": "openaps://cgm", 
    "unfiltered": 132224, 
    "rssi": 194, 
    "date": 1472152634000, 
    "filtered": 133472, 
    "type": "sgv", 
    "glucose": 123
  }, 
  {
    "trend_arrow": "FLAT", 
    "display_time": "2016-08-25T12:12:14-07:00", 
    "noise": 1, 
    "system_time": "2016-08-25T18:07:07-07:00", 
    "direction": "Flat", 
    "sgv": 125, 
    "dateString": "2016-08-25T12:12:14-07:00", 
    "device": "openaps://cgm", 
    "unfiltered": 133984, 
    "rssi": 208, 
    "date": 1472152334000, 
    "filtered": 132800, 
    "type": "sgv", 
    "glucose": 125
  }
]