[
  {
    "trend_arrow": "45_DOWN", 
    "display_time": "2016-09-13T00:21:07-07:00", 
    "noise": 1, 
    "direction": "FortyFiveDown", 
    "system_time": "2016-09-13T06:15:35-07:00", 
    "sgv": 165, 
    "dateString": "2016-09-13T00:21:07-07:00", 
    "device": "openaps://indy-e1/cgm", 
    "unfiltered": 183040, 
    "rssi": 188, 
    "date": 1473751267000.0, 
    "filtered": 193984, 
    "type": "sgv", 
    "glucose": 165
  }, 
  {
    "trend_arrow": "FLAT", 
    "display_time": "2016-09-13T00:16:07-07:00", 
    "noise": 1, 
    "direction": "Flat", 
    "system_time": "2016-09-13T06:10:35-07:00", 
    "sgv": 177, 
    "dateString": "2016-09-13T00:16:07-07:00", 
    "device": "openaps://indy-e1/cgm", 
    "unfiltered": 193568, 
    "rssi": 196, 
    "date": 1473750967000.0, 
    "filtered": 196992, 
    "type": "sgv", 
    "glucose": 177
  }, 
  {
    "trend_arrow": "FLAT", 
    "display_time": "2016-09-13T00:11:07-07:00", 
    "noise": 1, 
    "direction": "Flat", 
    "system_time": "2016-09-13T06:05:35-07:00", 
    "sgv": 178, 
    "dateString": "2016-09-13T00:11:07-07:00", 
    "device": "openaps://indy-e1/cgm", 
    "unfiltered": 194752, 
    "rssi": 194, 
    "date": 1473750667000.0, 
    "filtered": 197376, 
    "type": "sgv", 
    "glucose": 178
  }, 
  {
    "trend_arrow": "FLAT", 
    "display_time": "2016-09-13T00:06:07-07:00", 
    "noise": 1, 
    "direction": "Flat", 
    "system_time": "2016-09-13T06:00:35-07:00", 
    "sgv": 180, 
    "dateString": "2016-09-13T00:06:07-07:00", 
    "device": "openaps://indy-e1/cgm", 
    "unfiltered": 196096, 
    "rssi": 197, 
    "date": 1473750367000.0, 
    "filtered": 195968, 
    "type": "sgv", 
    "glucose": 180
  }, 
  {
    "trend_arrow": "FLAT", 
    "display_time": "2016-09-13T00:01:07-07:00", 
    "noise": 1, 
    "direction": "Flat", 
    "system_time": "2016-09-13T05:55:35-07:00", 
    "sgv": 183, 
    "dateString": "2016-09-13T00:01:07-07:00", 
    "device": "openaps://indy-e1/cgm", 
    "unfiltered": 199040, 
    "rssi": 197, 
    "date": 1473750067000.0, 
    "filtered": 194880, 
    "type": "sgv", 
    "glucose": 183
  }, 
  {
    "trend_arrow": "FLAT", 
    "display_time": "2016-09-12T23:56:07-07:00", 
    "noise": 1, 
    "direction": "Flat", 
    "system_time": "2016-09-13T05:50:35-07:00", 
    "sgv": 183, 
    "dateString": "2016-09-12T23:56:07-07:00", 
    "device": "openaps://indy-e1/cgm", 
    "unfiltered": 199360, 
    "rssi": 197, 
    "date": 1473749767000.0, 
    "filtered": 195648, 
    "type": "sgv", 
    "glucose": 183
  }
]