[
  {
    "trend_arrow": "45_UP", 
    "display_time": "2016-08-06T23:00:17-07:00", 
    "noise": 1, 
    "direction": "FortyFiveUp", 
    "system_time": "2016-08-07T05:50:23-07:00", 
    "sgv": 157, 
    "dateString": "2016-08-06T23:00:17-07:00", 
    "device": "openaps://cgm", 
    "unfiltered": 175552, 
    "rssi": 186, 
    "date": 1470549617000.0, 
    "filtered": 163936, 
    "type": "sgv", 
    "glucose": 157
  }, 
  {
    "trend_arrow": "45_UP", 
    "display_time": "2016-08-06T22:55:17-07:00", 
    "noise": 1, 
    "direction": "FortyFiveUp", 
    "system_time": "2016-08-07T05:45:24-07:00", 
    "sgv": 150, 
    "dateString": "2016-08-06T22:55:17-07:00", 
    "device": "openaps://cgm", 
    "unfiltered": 167968, 
    "rssi": 443, 
    "date": 1470549317000.0, 
    "filtered": 157856, 
    "type": "sgv", 
    "glucose": 150
  }, 
  {
    "trend_arrow": "FLAT", 
    "display_time": "2016-08-06T22:50:17-07:00", 
    "noise": 1, 
    "direction": "Flat", 
    "system_time": "2016-08-07T05:40:23-07:00", 
    "sgv": 143, 
    "dateString": "2016-08-06T22:50:17-07:00", 
    "device": "openaps://cgm", 
    "unfiltered": 161600, 
    "rssi": 187, 
    "date": 1470549017000.0, 
    "filtered": 153600, 
    "type": "sgv", 
    "glucose": 143
  }, 
  {
    "trend_arrow": "FLAT", 
    "display_time": "2016-08-06T22:45:17-07:00", 
    "noise": 1, 
    "direction": "Flat", 
    "system_time": "2016-08-07T05:35:23-07:00", 
    "sgv": 137, 
    "dateString": "2016-08-06T22:45:17-07:00", 
    "device": "openaps://cgm", 
    "unfiltered": 155808, 
    "rssi": 180, 
    "date": 1470548717000.0, 
    "filtered": 151360, 
    "type": "sgv", 
    "glucose": 137
  }, 
  {
    "trend_arrow": "FLAT", 
    "display_time": "2016-08-06T22:40:17-07:00", 
    "noise": 1, 
    "direction": "Flat", 
    "system_time": "2016-08-07T05:30:23-07:00", 
    "sgv": 133, 
    "dateString": "2016-08-06T22:40:17-07:00", 
    "device": "openaps://cgm", 
    "unfiltered": 151840, 
    "rssi": 181, 
    "date": 1470548417000.0, 
    "filtered": 150528, 
    "type": "sgv", 
    "glucose": 133
  }, 
  {
    "trend_arrow": "FLAT", 
    "display_time": "2016-08-06T22:35:17-07:00", 
    "noise": 1, 
    "direction": "Flat", 
    "system_time": "2016-08-07T05:25:23-07:00", 
    "sgv": 131, 
    "dateString": "2016-08-06T22:35:17-07:00", 
    "device": "openaps://cgm", 
    "unfiltered": 150208, 
    "rssi": 181, 
    "date": 1470548117000.0, 
    "filtered": 149952, 
    "type": "sgv", 
    "glucose": 131
  }
]