[
  {
    "trend_arrow": "FLAT", 
    "display_time": "2016-09-19T23:45:13-07:00", 
    "noise": 1, 
    "direction": "Flat", 
    "system_time": "2016-09-20T05:39:27-07:00", 
    "sgv": 165, 
    "dateString": "2016-09-19T23:45:13-07:00", 
    "device": "openaps://indy-e1/cgm", 
    "unfiltered": 171360, 
    "rssi": 191, 
    "date": 1474353913000.0, 
    "filtered": 166336, 
    "type": "sgv", 
    "glucose": 165
  }, 
  {
    "trend_arrow": "FLAT", 
    "display_time": "2016-09-19T23:40:13-07:00", 
    "noise": 1, 
    "direction": "Flat", 
    "system_time": "2016-09-20T05:34:27-07:00", 
    "sgv": 163, 
    "dateString": "2016-09-19T23:40:13-07:00", 
    "device": "openaps://indy-e1/cgm", 
    "unfiltered": 169600, 
    "rssi": 192, 
    "date": 1474353613000.0, 
    "filtered": 163008, 
    "type": "sgv", 
    "glucose": 163
  }, 
  {
    "trend_arrow": "FLAT", 
    "display_time": "2016-09-19T23:35:13-07:00", 
    "noise": 1, 
    "direction": "Flat", 
    "system_time": "2016-09-20T05:29:27-07:00", 
    "sgv": 158, 
    "dateString": "2016-09-19T23:35:13-07:00", 
    "device": "openaps://indy-e1/cgm", 
    "unfiltered": 164960, 
    "rssi": 187, 
    "date": 1474353313000.0, 
    "filtered": 160928, 
    "type": "sgv", 
    "glucose": 158
  }, 
  {
    "trend_arrow": "FLAT", 
    "display_time": "2016-09-19T23:30:13-07:00", 
    "noise": 1, 
    "direction": "Flat", 
    "system_time": "2016-09-20T05:24:27-07:00", 
    "sgv": 155, 
    "dateString": "2016-09-19T23:30:13-07:00", 
    "device": "openaps://indy-e1/cgm", 
    "unfiltered": 162432, 
    "rssi": 187, 
    "date": 1474353013000.0, 
    "filtered": 160192, 
    "type": "sgv", 
    "glucose": 155
  }, 
  {
    "trend_arrow": "FLAT", 
    "display_time": "2016-09-19T23:25:13-07:00", 
    "noise": 1, 
    "direction": "Flat", 
    "system_time": "2016-09-20T05:19:27-07:00", 
    "sgv": 151, 
    "dateString": "2016-09-19T23:25:13-07:00", 
    "device": "openaps://indy-e1/cgm", 
    "unfiltered": 159040, 
    "rssi": 187, 
    "date": 1474352713000.0, 
    "filtered": 159872, 
    "type": "sgv", 
    "glucose": 151
  }, 
  {
    "trend_arrow": "FLAT", 
    "display_time": "2016-09-19T23:20:13-07:00", 
    "noise": 1, 
    "direction": "Flat", 
    "system_time": "2016-09-20T05:14:27-07:00", 
    "sgv": 152, 
    "dateString": "2016-09-19T23:20:13-07:00", 
    "device": "openaps://indy-e1/cgm", 
    "unfiltered": 159680, 
    "rssi": 188, 
    "date": 1474352413000.0, 
    "filtered": 159264, 
    "type": "sgv", 
    "glucose": 152
  }
]