[
  {
    "trend_arrow": "FLAT", 
    "display_time": "2016-08-04T05:25:31-07:00", 
    "noise": 1, 
    "direction": "Flat", 
    "system_time": "2016-08-04T12:15:38-07:00", 
    "sgv": 137, 
    "dateString": "2016-08-04T05:25:31-07:00", 
    "device": "openaps://cgm", 
    "unfiltered": 153696, 
    "rssi": 190, 
    "date": 1470313531000.0, 
    "filtered": 161344, 
    "type": "sgv", 
    "glucose": 137
  }, 
  {
    "trend_arrow": "FLAT", 
    "display_time": "2016-08-04T05:20:31-07:00", 
    "noise": 1, 
    "direction": "Flat", 
    "system_time": "2016-08-04T12:10:38-07:00", 
    "sgv": 142, 
    "dateString": "2016-08-04T05:20:31-07:00", 
    "device": "openaps://cgm", 
    "unfiltered": 158368, 
    "rssi": 190, 
    "date": 1470313231000.0, 
    "filtered": 164128, 
    "type": "sgv", 
    "glucose": 142
  }, 
  {
    "trend_arrow": "FLAT", 
    "display_time": "2016-08-04T05:15:31-07:00", 
    "noise": 1, 
    "direction": "Flat", 
    "system_time": "2016-08-04T12:05:38-07:00", 
    "sgv": 146, 
    "dateString": "2016-08-04T05:15:31-07:00", 
    "device": "openaps://cgm", 
    "unfiltered": 161824, 
    "rssi": 192, 
    "date": 1470312931000.0, 
    "filtered": 163904, 
    "type": "sgv", 
    "glucose": 146
  }, 
  {
    "trend_arrow": "FLAT", 
    "display_time": "2016-08-04T05:10:32-07:00", 
    "noise": 1, 
    "direction": "Flat", 
    "system_time": "2016-08-04T12:00:38-07:00", 
    "sgv": 148, 
    "dateString": "2016-08-04T05:10:32-07:00", 
    "device": "openaps://cgm", 
    "unfiltered": 164544, 
    "rssi": 192, 
    "date": 1470312632000.0, 
    "filtered": 160800, 
    "type": "sgv", 
    "glucose": 148
  }, 
  {
    "trend_arrow": "45_UP", 
    "display_time": "2016-08-04T05:05:31-07:00", 
    "noise": 1, 
    "direction": "FortyFiveUp", 
    "system_time": "2016-08-04T11:55:38-07:00", 
    "sgv": 148, 
    "dateString": "2016-08-04T05:05:31-07:00", 
    "device": "openaps://cgm", 
    "unfiltered": 164384, 
    "rssi": 197, 
    "date": 1470312331000.0, 
    "filtered": 155904, 
    "type": "sgv", 
    "glucose": 148
  }, 
  {
    "trend_arrow": "45_UP", 
    "display_time": "2016-08-04T05:00:31-07:00", 
    "noise": 1, 
    "direction": "FortyFiveUp", 
    "system_time": "2016-08-04T11:50:38-07:00", 
    "sgv": 142, 
    "dateString": "2016-08-04T05:00:31-07:00", 
    "device": "openaps://cgm", 
    "unfiltered": 158912, 
    "rssi": 195, 
    "date": 1470312031000.0, 
    "filtered": 150272, 
    "type": "sgv", 
    "glucose": 142
  }
]