[
  {
    "trend_arrow": "45_DOWN", 
    "display_time": "2016-09-20T09:55:12-07:00", 
    "noise": 1, 
    "direction": "FortyFiveDown", 
    "system_time": "2016-09-20T15:49:25-07:00", 
    "sgv": 88, 
    "dateString": "2016-09-20T09:55:12-07:00", 
    "device": "openaps://indy-e1/cgm", 
    "unfiltered": 104112, 
    "rssi": 190, 
    "date": 1474390512000.0, 
    "filtered": 114240, 
    "type": "sgv", 
    "glucose": 88
  }, 
  {
    "trend_arrow": "45_DOWN", 
    "display_time": "2016-09-20T09:50:12-07:00", 
    "noise": 1, 
    "direction": "FortyFiveDown", 
    "system_time": "2016-09-20T15:44:25-07:00", 
    "sgv": 95, 
    "dateString": "2016-09-20T09:50:12-07:00", 
    "device": "openaps://indy-e1/cgm", 
    "unfiltered": 109616, 
    "rssi": 177, 
    "date": 1474390212000.0, 
    "filtered": 121488, 
    "type": "sgv", 
    "glucose": 95
  }, 
  {
    "trend_arrow": "45_DOWN", 
    "display_time": "2016-09-20T09:45:12-07:00", 
    "noise": 1, 
    "direction": "FortyFiveDown", 
    "system_time": "2016-09-20T15:39:26-07:00", 
    "sgv": 104, 
    "dateString": "2016-09-20T09:45:12-07:00", 
    "device": "openaps://indy-e1/cgm", 
    "unfiltered": 117392, 
    "rssi": 450, 
    "date": 1474389912000.0, 
    "filtered": 128528, 
    "type": "sgv", 
    "glucose": 104
  }, 
  {
    "trend_arrow": "45_DOWN", 
    "display_time": "2016-09-20T09:40:12-07:00", 
    "noise": 1, 
    "direction": "FortyFiveDown", 
    "system_time": "2016-09-20T15:34:26-07:00", 
    "sgv": 114, 
    "dateString": "2016-09-20T09:40:12-07:00", 
    "device": "openaps://indy-e1/cgm", 
    "unfiltered": 125264, 
    "rssi": 441, 
    "date": 1474389612000.0, 
    "filtered": 135232, 
    "type": "sgv", 
    "glucose": 114
  }, 
  {
    "trend_arrow": "45_DOWN", 
    "display_time": "2016-09-20T09:35:12-07:00", 
    "noise": 1, 
    "direction": "FortyFiveDown", 
    "system_time": "2016-09-20T15:29:25-07:00", 
    "sgv": 121, 
    "dateString": "2016-09-20T09:35:12-07:00", 
    "device": "openaps://indy-e1/cgm", 
    "unfiltered": 131872, 
    "rssi": 173, 
    "date": 1474389312000.0, 
    "filtered": 141600, 
    "type": "sgv", 
    "glucose": 121
  }, 
  {
    "trend_arrow": "45_DOWN", 
    "display_time": "2016-09-20T09:30:12-07:00", 
    "noise": 1, 
    "direction": "FortyFiveDown", 
    "system_time": "2016-09-20T15:24:25-07:00", 
    "sgv": 129, 
    "dateString": "2016-09-20T09:30:12-07:00", 
    "device": "openaps://indy-e1/cgm", 
    "unfiltered": 137792, 
    "rssi": 192, 
    "date": 1474389012000.0, 
    "filtered": 147456, 
    "type": "sgv", 
    "glucose": 129
  }
]