[
  {
    "trend_arrow": "45_UP", 
    "display_time": "2016-09-12T13:51:09-07:00", 
    "noise": 2, 
    "direction": "FortyFiveUp", 
    "system_time": "2016-09-12T19:45:37-07:00", 
    "sgv": 159, 
    "dateString": "2016-09-12T13:51:09-07:00", 
    "device": "openaps://indy-e1/cgm", 
    "unfiltered": 141472, 
    "rssi": 198, 
    "date": 1473713469000.0, 
    "filtered": 143872, 
    "type": "sgv", 
    "glucose": 159
  }, 
  {
    "trend_arrow": "45_UP", 
    "display_time": "2016-09-12T13:46:09-07:00", 
    "noise": 1, 
    "direction": "FortyFiveUp", 
    "system_time": "2016-09-12T19:40:37-07:00", 
    "sgv": 164, 
    "dateString": "2016-09-12T13:46:09-07:00", 
    "device": "openaps://indy-e1/cgm", 
    "unfiltered": 148032, 
    "rssi": 197, 
    "date": 1473713169000.0, 
    "filtered": 136512, 
    "type": "sgv", 
    "glucose": 164
  }, 
  {
    "trend_arrow": "45_UP", 
    "display_time": "2016-09-12T13:41:09-07:00", 
    "noise": 1, 
    "direction": "FortyFiveUp", 
    "system_time": "2016-09-12T19:35:37-07:00", 
    "sgv": 161, 
    "dateString": "2016-09-12T13:41:09-07:00", 
    "device": "openaps://indy-e1/cgm", 
    "unfiltered": 145568, 
    "rssi": 191, 
    "date": 1473712869000.0, 
    "filtered": 129536, 
    "type": "sgv", 
    "glucose": 161
  }, 
  {
    "trend_arrow": "FLAT", 
    "display_time": "2016-09-12T13:36:09-07:00", 
    "noise": 1, 
    "direction": "Flat", 
    "system_time": "2016-09-12T19:30:37-07:00", 
    "sgv": 148, 
    "dateString": "2016-09-12T13:36:09-07:00", 
    "device": "openaps://indy-e1/cgm", 
    "unfiltered": 135744, 
    "rssi": 197, 
    "date": 1473712569000.0, 
    "filtered": 126832, 
    "type": "sgv", 
    "glucose": 148
  }, 
  {
    "trend_arrow": "FLAT", 
    "display_time": "2016-09-12T13:31:09-07:00", 
    "noise": 1, 
    "direction": "Flat", 
    "system_time": "2016-09-12T19:25:37-07:00", 
    "sgv": 134, 
    "dateString": "2016-09-12T13:31:09-07:00", 
    "device": "openaps://indy-e1/cgm", 
    "unfiltered": 125536, 
    "rssi": 201, 
    "date": 1473712269000.0, 
    "filtered": 127152, 
    "type": "sgv", 
    "glucose": 134
  }, 
  {
    "trend_arrow": "FLAT", 
    "display_time": "2016-09-12T13:26:09-07:00", 
    "noise": 1, 
    "direction": "Flat", 
    "system_time": "2016-09-12T19:20:37-07:00", 
    "sgv": 129, 
    "dateString": "2016-09-12T13:26:09-07:00", 
    "device": "openaps://indy-e1/cgm", 
    "unfiltered": 121936, 
    "rssi": 196, 
    "date": 1473711969000.0, 
    "filtered": 126528, 
    "type": "sgv", 
    "glucose": 129
  }
]