[
  {
    "trend_arrow": "FLAT", 
    "display_time": "2016-08-29T01:50:59-07:00", 
    "noise": 1, 
    "direction": "Flat", 
    "system_time": "2016-08-29T07:45:42-07:00", 
    "sgv": 133, 
    "dateString": "2016-08-29T01:50:59-07:00", 
    "device": "openaps://cgm", 
    "unfiltered": 148800, 
    "rssi": 195, 
    "date": 1472460659000.0, 
    "filtered": 154240, 
    "type": "sgv", 
    "glucose": 133
  }, 
  {
    "trend_arrow": "45_DOWN", 
    "display_time": "2016-08-29T01:45:59-07:00", 
    "noise": 1, 
    "direction": "FortyFiveDown", 
    "system_time": "2016-08-29T07:40:42-07:00", 
    "sgv": 138, 
    "dateString": "2016-08-29T01:45:59-07:00", 
    "device": "openaps://cgm", 
    "unfiltered": 152320, 
    "rssi": 197, 
    "date": 1472460359000.0, 
    "filtered": 158144, 
    "type": "sgv", 
    "glucose": 138
  }, 
  {
    "trend_arrow": "45_DOWN", 
    "display_time": "2016-08-29T01:40:59-07:00", 
    "noise": 1, 
    "direction": "FortyFiveDown", 
    "system_time": "2016-08-29T07:35:42-07:00", 
    "sgv": 142, 
    "dateString": "2016-08-29T01:40:59-07:00", 
    "device": "openaps://cgm", 
    "unfiltered": 156224, 
    "rssi": 197, 
    "date": 1472460059000.0, 
    "filtered": 162816, 
    "type": "sgv", 
    "glucose": 142
  }, 
  {
    "trend_arrow": "45_DOWN", 
    "display_time": "2016-08-29T01:35:59-07:00", 
    "noise": 1, 
    "direction": "FortyFiveDown", 
    "system_time": "2016-08-29T07:30:42-07:00", 
    "sgv": 148, 
    "dateString": "2016-08-29T01:35:59-07:00", 
    "device": "openaps://cgm", 
    "unfiltered": 160672, 
    "rssi": 197, 
    "date": 1472459759000.0, 
    "filtered": 168768, 
    "type": "sgv", 
    "glucose": 148
  }, 
  {
    "trend_arrow": "45_DOWN", 
    "display_time": "2016-08-29T01:30:59-07:00", 
    "noise": 1, 
    "direction": "FortyFiveDown", 
    "system_time": "2016-08-29T07:25:42-07:00", 
    "sgv": 154, 
    "dateString": "2016-08-29T01:30:59-07:00", 
    "device": "openaps://cgm", 
    "unfiltered": 165664, 
    "rssi": 195, 
    "date": 1472459459000.0, 
    "filtered": 176128, 
    "type": "sgv", 
    "glucose": 154
  }, 
  {
    "trend_arrow": "SINGLE_DOWN", 
    "display_time": "2016-08-29T01:25:59-07:00", 
    "noise": 1, 
    "direction": "SingleDown", 
    "system_time": "2016-08-29T07:20:42-07:00", 
    "sgv": 161, 
    "dateString": "2016-08-29T01:25:59-07:00", 
    "device": "openaps://cgm", 
    "unfiltered": 171552, 
    "rssi": 197, 
    "date": 1472459159000.0, 
    "filtered": 184640, 
    "type": "sgv", 
    "glucose": 161
  }
]