[
  {
    "trend_arrow": "FLAT", 
    "display_time": "2016-08-12T08:39:58-07:00", 
    "noise": 1, 
    "direction": "Flat", 
    "system_time": "2016-08-12T14:35:23-07:00", 
    "sgv": 113, 
    "dateString": "2016-08-12T08:39:58-07:00", 
    "device": "openaps://cgm", 
    "unfiltered": 100144, 
    "rssi": 185, 
    "date": 1471016398000.0, 
    "filtered": 101008, 
    "type": "sgv", 
    "glucose": 113
  }, 
  {
    "trend_arrow": "FLAT", 
    "display_time": "2016-08-12T08:34:58-07:00", 
    "noise": 1, 
    "direction": "Flat", 
    "system_time": "2016-08-12T14:30:24-07:00", 
    "sgv": 115, 
    "dateString": "2016-08-12T08:34:58-07:00", 
    "device": "openaps://cgm", 
    "unfiltered": 101296, 
    "rssi": 443, 
    "date": 1471016098000.0, 
    "filtered": 104160, 
    "type": "sgv", 
    "glucose": 115
  }, 
  {
    "trend_arrow": "FLAT", 
    "display_time": "2016-08-12T08:29:58-07:00", 
    "noise": 1, 
    "direction": "Flat", 
    "system_time": "2016-08-12T14:25:23-07:00", 
    "sgv": 115, 
    "dateString": "2016-08-12T08:29:58-07:00", 
    "device": "openaps://cgm", 
    "unfiltered": 101984, 
    "rssi": 192, 
    "date": 1471015798000.0, 
    "filtered": 107792, 
    "type": "sgv", 
    "glucose": 115
  }, 
  {
    "trend_arrow": "FLAT", 
    "display_time": "2016-08-12T08:24:58-07:00", 
    "noise": 1, 
    "direction": "Flat", 
    "system_time": "2016-08-12T14:20:23-07:00", 
    "sgv": 117, 
    "dateString": "2016-08-12T08:24:58-07:00", 
    "device": "openaps://cgm", 
    "unfiltered": 102976, 
    "rssi": 181, 
    "date": 1471015498000.0, 
    "filtered": 109136, 
    "type": "sgv", 
    "glucose": 117
  }, 
  {
    "trend_arrow": "FLAT", 
    "display_time": "2016-08-12T08:19:58-07:00", 
    "noise": 1, 
    "direction": "Flat", 
    "system_time": "2016-08-12T14:15:24-07:00", 
    "sgv": 121, 
    "dateString": "2016-08-12T08:19:58-07:00", 
    "device": "openaps://cgm", 
    "unfiltered": 106416, 
    "rssi": 438, 
    "date": 1471015198000.0, 
    "filtered": 107408, 
    "type": "sgv", 
    "glucose": 121
  }, 
  {
    "trend_arrow": "FLAT", 
    "display_time": "2016-08-12T08:14:58-07:00", 
    "noise": 2, 
    "direction": "Flat", 
    "system_time": "2016-08-12T14:10:24-07:00", 
    "sgv": 120, 
    "dateString": "2016-08-12T08:14:58-07:00", 
    "device": "openaps://cgm", 
    "unfiltered": 112992, 
    "rssi": 427, 
    "date": 1471014898000.0, 
    "filtered": 105408, 
    "type": "sgv", 
    "glucose": 120
  }
]