[
  {
    "trend_arrow": "FLAT", 
    "display_time": "2016-08-25T10:12:14-07:00", 
    "noise": 1, 
    "system_time": "2016-08-25T16:07:08-07:00", 
    "direction": "Flat", 
    "sgv": 102, 
    "dateString": "2016-08-25T10:12:14-07:00", 
    "device": "openaps://cgm", 
    "unfiltered": 115392, 
    "rssi": 194, 
    "date": 1472145134000, 
    "filtered": 112320, 
    "type": "sgv", 
    "glucose": 102
  }, 
  {
    "trend_arrow": "FLAT", 
    "display_time": "2016-08-25T10:07:14-07:00", 
    "noise": 1, 
    "system_time": "2016-08-25T16:02:08-07:00", 
    "direction": "Flat", 
    "sgv": 101, 
    "dateString": "2016-08-25T10:07:14-07:00", 
    "device": "openaps://cgm", 
    "unfiltered": 114640, 
    "rssi": 210, 
    "date": 1472144834000, 
    "filtered": 110752, 
    "type": "sgv", 
    "glucose": 101
  }
]