[
  {
    "trend_arrow": "FLAT", 
    "display_time": "2016-08-21T04:17:35-07:00", 
    "noise": 1, 
    "system_time": "2016-08-21T10:12:28-07:00", 
    "direction": "Flat", 
    "sgv": 180, 
    "dateString": "2016-08-21T04:17:35-07:00", 
    "device": "openaps://cgm", 
    "unfiltered": 212064, 
    "rssi": 176, 
    "date": 1471778255000, 
    "filtered": 206112, 
    "type": "sgv", 
    "glucose": 180
  }, 
  {
    "trend_arrow": "FLAT", 
    "display_time": "2016-08-21T04:12:35-07:00", 
    "noise": 1, 
    "system_time": "2016-08-21T10:07:28-07:00", 
    "direction": "Flat", 
    "sgv": 176, 
    "dateString": "2016-08-21T04:12:35-07:00", 
    "device": "openaps://cgm", 
    "unfiltered": 208736, 
    "rssi": 175, 
    "date": 1471777955000, 
    "filtered": 203648, 
    "type": "sgv", 
    "glucose": 176
  }
]